[
  {
    "name": "Jagannath Mondal",
    "plan": "@29 Plan",
    "mobile": "7908832878",
    "contactMethod": "whatsapp",
    "contactDetail": "7908832878",
    "timestamp": "2025-08-29T12:58:40.926Z"
  },
  {
    "name": "Jagannath Mondal",
    "plan": "@29 Plan",
    "mobile": "7908832878",
    "contactMethod": "whatsapp",
    "contactDetail": "7908832878",
    "timestamp": "2025-08-29T12:58:43.684Z"
  },
  {
    "name": "Mukul",
    "plan": "@39 Plan",
    "mobile": "8307124799",
    "contactMethod": "telegram",
    "contactDetail": "Vishwaso",
    "timestamp": "2025-09-02T02:18:20.701Z"
  }
]